tempoggl/__init__.py
tempoggl/__main__.py
tempoggl/cli.py
tempoggl/config.py
tempoggl/tempo.py
tempoggl/toggl.py
tempoggl/typing_tools.py
test/__init__.py
test/conftest.py
test/test_config.py
test/test_tempo.py
test/test_toggl.py
Tempoggl-1.3.3.dist-info/METADATA
Tempoggl-1.3.3.dist-info/WHEEL
Tempoggl-1.3.3.dist-info/entry_points.txt
Tempoggl-1.3.3.dist-info/top_level.txt
Tempoggl-1.3.3.dist-info/RECORD
