Metadata-Version: 2.1
Name: Tempoggl
Version: 1.3.3
Summary: UNKNOWN
Home-page: https://github.com/je-l/tempoggl
Author: UNKNOWN
Author-email: UNKNOWN
License: UNKNOWN
Platform: UNKNOWN
Requires-Dist: pyhumps (<3.0.0,>=1.2.2)
Requires-Dist: pydantic (<2.0.0,>=1.0.0)
Requires-Dist: requests (<3.0.0,>=2.21.0)
Requires-Dist: python-dateutil (<3.0.0,>=2.0)
Requires-Dist: tzlocal (<3.0.0,>=2.0.0)
Requires-Dist: importlib-metadata (<2.0.0,>=1.5.0)
